hexqbot/__init__.py
hexqbot-0.0.1.dist-info/METADATA
hexqbot-0.0.1.dist-info/WHEEL
hexqbot-0.0.1.dist-info/top_level.txt
hexqbot-0.0.1.dist-info/RECORD
