Metadata-Version: 2.1
Name: hexqbot
Version: 0.0.1
Summary: HexQBot API for Python
Home-page: https://chat.hexqbot.xyz
Author: hexqbot
Author-email: slightwindsec@gmail.com
